mylib007/__init__.py
mylib007-0.1.dist-info/LICENSE.txt
mylib007-0.1.dist-info/METADATA
mylib007-0.1.dist-info/WHEEL
mylib007-0.1.dist-info/top_level.txt
mylib007-0.1.dist-info/RECORD
